pydantic_argify/__init__.py
pydantic_argify/__version__.py
pydantic_argify/cli.py
pydantic_argify/config.py
pydantic_argify/parse.py
pydantic_argify-0.4.5.dist-info/LICENSE
pydantic_argify-0.4.5.dist-info/METADATA
pydantic_argify-0.4.5.dist-info/WHEEL
pydantic_argify-0.4.5.dist-info/RECORD
